score/html/__init__.py
score.html-0.1.dist-info/DESCRIPTION.rst
score.html-0.1.dist-info/METADATA
score.html-0.1.dist-info/RECORD
score.html-0.1.dist-info/WHEEL
score.html-0.1.dist-info/metadata.json
score.html-0.1.dist-info/top_level.txt
